Metadata-Version: 2.1
Name: django-image-assets
Version: 1.0.0
Summary: Django application for image assets management
Author-email: Sergey Tikhonov <zimbler@gmail.com>
License: MIT
Project-URL: homepage, https://github.com/just-work/django-image-assets
Project-URL: documentation, https://github.com/just-work/django-image-assets/blob/master/README.md
Project-URL: repository, https://github.com/just-work/django-image-assets.git
Project-URL: issues, https://github.com/just-work/django-image-assets/issues
Keywords: django,image,assets
Classifier: Development Status :: 4 - Beta
Classifier: Environment :: Console
Classifier: Framework :: Django :: 3.2
Classifier: Framework :: Django :: 4.0
Classifier: Framework :: Django :: 4.1
Classifier: Framework :: Django :: 4.2
Classifier: Framework :: Django :: 5.0
Classifier: Operating System :: POSIX
Classifier: Programming Language :: Python :: 3.8
Classifier: Programming Language :: Python :: 3.9
Classifier: Programming Language :: Python :: 3.10
Classifier: Programming Language :: Python :: 3.11
Classifier: Programming Language :: Python :: 3.12
Classifier: Topic :: Internet :: WWW/HTTP :: Dynamic Content :: Content Management System
License-File: LICENSE
Requires-Dist: Django <5.1,>=2.2
Requires-Dist: django-bitfield ~=2.0
Requires-Dist: Pillow <11.0.0,>=8.1.2
